dpea_odrive/__init__.py
dpea_odrive/odrive_helpers.py
dpea_odrive-1.1.1.dist-info/METADATA
dpea_odrive-1.1.1.dist-info/WHEEL
dpea_odrive-1.1.1.dist-info/licenses/LICENSE
dpea_odrive-1.1.1.dist-info/RECORD
