Metadata-Version: 2.3
Name: dpea_odrive
Version: 1.1.1
Summary: DPEA helper tool for running ODrive boards
Project-URL: Homepage, https://github.com/dpengineering/dpea-odrive
Author: Cesar Plascencia-Zuniga, Lyle Harlow
License-File: LICENSE
Classifier: License :: OSI Approved :: GNU General Public License (GPL)
Classifier: Operating System :: OS Independent
Classifier: Programming Language :: Python :: 3
Requires-Python: >=3.7
